{"trial_id": "0476", "hyperparameters": {"space": [{"class_name": "Choice", "config": {"name": "activation", "default": "relu", "conditions": [], "values": ["relu", "gelu", "selu"], "ordered": false}}, {"class_name": "Int", "config": {"name": "first_units", "default": null, "conditions": [], "min_value": 1, "max_value": 256, "step": 7, "sampling": "linear"}}, {"class_name": "Int", "config": {"name": "num_layers", "default": null, "conditions": [], "min_value": 1, "max_value": 5, "step": 1, "sampling": "linear"}}, {"class_name": "Int", "config": {"name": "units_0", "default": null, "conditions": [], "min_value": 32, "max_value": 256, "step": 16, "sampling": "linear"}}, {"class_name": "Choice", "config": {"name": "learning_rate", "default": 1.0, "conditions": [], "values": [1.0, 0.1, 0.01, 0.001, 0.0001], "ordered": true}}, {"class_name": "Int", "config": {"name": "units_1", "default": null, "conditions": [], "min_value": 32, "max_value": 256, "step": 16, "sampling": "linear"}}, {"class_name": "Int", "config": {"name": "units_2", "default": null, "conditions": [], "min_value": 32, "max_value": 256, "step": 16, "sampling": "linear"}}, {"class_name": "Int", "config": {"name": "units_3", "default": null, "conditions": [], "min_value": 32, "max_value": 256, "step": 16, "sampling": "linear"}}, {"class_name": "Int", "config": {"name": "units_4", "default": null, "conditions": [], "min_value": 32, "max_value": 256, "step": 16, "sampling": "linear"}}], "values": {"activation": "gelu", "first_units": 127, "num_layers": 3, "units_0": 240, "learning_rate": 0.001, "units_1": 144, "units_2": 256, "units_3": 224, "units_4": 240, "tuner/epochs": 34, "tuner/initial_epoch": 12, "tuner/bracket": 2, "tuner/round": 1, "tuner/trial_id": "0463"}}, "metrics": {"metrics": {"loss": {"direction": "min", "observations": [{"value": [0.8774316906929016], "step": 21}]}, "mean_squared_error": {"direction": "min", "observations": [{"value": [3.0440454483032227], "step": 21}]}, "val_loss": {"direction": "min", "observations": [{"value": [3.2549684047698975], "step": 21}]}, "val_mean_squared_error": {"direction": "min", "observations": [{"value": [31.55170249938965], "step": 21}]}}}, "score": 3.0440454483032227, "best_step": 21, "status": "COMPLETED", "message": null}