{"trial_id": "0166", "hyperparameters": {"space": [{"class_name": "Choice", "config": {"name": "activation", "default": "relu", "conditions": [], "values": ["relu", "gelu", "selu"], "ordered": false}}, {"class_name": "Int", "config": {"name": "first_units", "default": null, "conditions": [], "min_value": 1, "max_value": 256, "step": 7, "sampling": "linear"}}, {"class_name": "Int", "config": {"name": "num_layers", "default": null, "conditions": [], "min_value": 1, "max_value": 5, "step": 1, "sampling": "linear"}}, {"class_name": "Int", "config": {"name": "units_0", "default": null, "conditions": [], "min_value": 32, "max_value": 256, "step": 16, "sampling": "linear"}}, {"class_name": "Choice", "config": {"name": "learning_rate", "default": 1.0, "conditions": [], "values": [1.0, 0.1, 0.01, 0.001, 0.0001], "ordered": true}}, {"class_name": "Int", "config": {"name": "units_1", "default": null, "conditions": [], "min_value": 32, "max_value": 256, "step": 16, "sampling": "linear"}}, {"class_name": "Int", "config": {"name": "units_2", "default": null, "conditions": [], "min_value": 32, "max_value": 256, "step": 16, "sampling": "linear"}}, {"class_name": "Int", "config": {"name": "units_3", "default": null, "conditions": [], "min_value": 32, "max_value": 256, "step": 16, "sampling": "linear"}}, {"class_name": "Int", "config": {"name": "units_4", "default": null, "conditions": [], "min_value": 32, "max_value": 256, "step": 16, "sampling": "linear"}}], "values": {"activation": "gelu", "first_units": 57, "num_layers": 3, "units_0": 64, "learning_rate": 0.001, "units_1": 128, "units_2": 256, "units_3": 144, "units_4": 80, "tuner/epochs": 4, "tuner/initial_epoch": 0, "tuner/bracket": 3, "tuner/round": 0}}, "metrics": {"metrics": {"loss": {"direction": "min", "observations": [{"value": [3.5504491329193115], "step": 3}]}, "mean_squared_error": {"direction": "min", "observations": [{"value": [36.44184112548828], "step": 3}]}, "val_loss": {"direction": "min", "observations": [{"value": [4.214198112487793], "step": 3}]}, "val_mean_squared_error": {"direction": "min", "observations": [{"value": [55.187564849853516], "step": 3}]}}}, "score": 36.44184112548828, "best_step": 3, "status": "COMPLETED", "message": null}